integresql_client_python/__init__.py
integresql_client_python/errors.py
integresql_client_python-0.9.2.dist-info/LICENSE
integresql_client_python-0.9.2.dist-info/METADATA
integresql_client_python-0.9.2.dist-info/WHEEL
integresql_client_python-0.9.2.dist-info/top_level.txt
integresql_client_python-0.9.2.dist-info/RECORD
