Metadata-Version: 2.1
Name: integresql-client-python
Version: 0.9.2
Summary: UNKNOWN
Home-page: https://github.com/msztolcman/integresql-client-python
Author: Marcin Sztolcman
Author-email: marcin@urzenia.net
License: MIT
Download-URL: https://github.com/msztolcman/integresql-client-python
Project-URL: GitHub: issues, https://github.com/msztolcman/integresql-client-python/issues
Project-URL: GitHub: repo, https://github.com/msztolcman/integresql-client-python
Platform: UNKNOWN
Classifier: Development Status :: 4 - Beta
Classifier: Intended Audience :: Developers
Classifier: Intended Audience :: System Administrators
Classifier: License :: OSI Approved :: MIT License
Classifier: Programming Language :: Python
Classifier: Programming Language :: Python :: 3
Classifier: Programming Language :: Python :: 3 :: Only
Classifier: Programming Language :: Python :: 3.8
Classifier: Programming Language :: Python :: 3.9
Classifier: Programming Language :: Python :: 3.10
Classifier: Topic :: Database
Classifier: Topic :: Software Development
Classifier: Topic :: Software Development :: Libraries
Classifier: Topic :: Software Development :: Quality Assurance
Classifier: Topic :: Software Development :: Testing
Classifier: Topic :: Software Development :: Testing :: BDD
Classifier: Topic :: Software Development :: Testing :: Mocking
Classifier: Topic :: Software Development :: Testing :: Unit
Requires-Python: >=3.8
Requires-Dist: requests
